{
  "type": "FeatureCollection",
  "features": [
    {
      "type": "Feature",
      "properties": {
        "name": "Auschwitz-Birkenau",
        "type": "Extermination Camp",
        "deaths": "~1,100,000",
        "start_year": 1940,
        "end_year": 1945
      },
      "geometry": {
        "type": "Point",
        "coordinates": [19.1783, 50.0359]
      }
    },
    {
      "type": "Feature",
      "properties": {
        "name": "Treblinka",
        "type": "Extermination Camp",
        "deaths": "~900,000",
        "start_year": 1942,
        "end_year": 1943
      },
      "geometry": {
        "type": "Point",
        "coordinates": [22.0250, 52.6583]
      }
    },
    {
      "type": "Feature",
      "properties": {
        "name": "Dachau",
        "type": "Labor Camp",
        "deaths": "~40,000",
        "start_year": 1933,
        "end_year": 1945
      },
      "geometry": {
        "type": "Point",
        "coordinates": [11.4340, 48.2612]
      }
    }
  ]
}
